{
  "cli": {
    "version": ">= 0.52.0"
  },
  "build": {
    "development": {
      "developmentClient": true,
      "distribution": "internal"
    },
    "preview": {
      "ios": {
        "simulator": true,
        "appleTeamId": "WQS4A6LBYK",
        "appleId": "v.dimitrov@uploy.app"
      }
    },
    "production": {}
  },
  "submit": {
    "production": {
      "ios": {
        "appleId": "v.dimitrov@uploy.app",
        "ascAppId": "1632827633",
        "appleTeamId": "WQS4A6LBYK"
      }
    }
  }
}
